nellie_api/__init__.py
nellie_api/client.py
nellie_api/types.py
nellie_api/webhooks.py
nellie_api-0.1.0.dist-info/METADATA
nellie_api-0.1.0.dist-info/WHEEL
nellie_api-0.1.0.dist-info/licenses/LICENSE
nellie_api-0.1.0.dist-info/RECORD
