Metadata-Version: 2.4
Name: nellie-api
Version: 0.1.0
Summary: Python client for the Nellie AI Book Generation API
Project-URL: Homepage, https://nelliewriter.com
Project-URL: Repository, https://github.com/buzzlellc/nellie-python
Project-URL: Documentation, https://nelliewriter.com/docs
License-Expression: MIT
License-File: LICENSE
Keywords: ai,api,book,generation,nellie
Classifier: Development Status :: 4 - Beta
Classifier: Intended Audience :: Developers
Classifier: License :: OSI Approved :: MIT License
Classifier: Programming Language :: Python :: 3
Classifier: Programming Language :: Python :: 3.8
Classifier: Programming Language :: Python :: 3.9
Classifier: Programming Language :: Python :: 3.10
Classifier: Programming Language :: Python :: 3.11
Classifier: Programming Language :: Python :: 3.12
Requires-Python: >=3.8
Requires-Dist: requests>=2.25.0
Requires-Dist: typing-extensions>=4.0.0; python_version < '3.11'
